macaw_adapters/__init__.py
macaw_adapters/anthropic/__init__.py
macaw_adapters/anthropic/secure_anthropic.py
macaw_adapters/langchain/__init__.py
macaw_adapters/langchain/_utils.py
macaw_adapters/langchain/agents.py
macaw_adapters/langchain/anthropic.py
macaw_adapters/langchain/callbacks.py
macaw_adapters/langchain/memory.py
macaw_adapters/langchain/openai.py
macaw_adapters/langchain/tools.py
macaw_adapters/mcp/__init__.py
macaw_adapters/mcp/client.py
macaw_adapters/mcp/decorators.py
macaw_adapters/mcp/fastmcp_compat.py
macaw_adapters/mcp/mcp.py
macaw_adapters/mcp/server.py
macaw_adapters/mcp/subscriptions.py
macaw_adapters/openai/__init__.py
macaw_adapters/openai/secure_openai.py
macaw_adapters-0.5.24.dist-info/licenses/LICENSE
macaw_adapters-0.5.24.dist-info/licenses/NOTICE
macaw_adapters-0.5.24.dist-info/METADATA
macaw_adapters-0.5.24.dist-info/WHEEL
macaw_adapters-0.5.24.dist-info/top_level.txt
macaw_adapters-0.5.24.dist-info/RECORD
