Metadata-Version: 2.4
Name: macaw-adapters
Version: 0.5.24
Summary: Secure AI Adapters for OpenAI, Claude, LangChain, and MCP
Author-email: MACAW Security <support@macawsecurity.com>
License: Apache-2.0
Project-URL: Homepage, https://macawsecurity.ai
Project-URL: Documentation, https://macawsecurity.ai/docs
Project-URL: Repository, https://github.com/macawsecurity/secureAI
Project-URL: Console, https://console.macawsecurity.ai
Keywords: ai,security,openai,claude,langchain,mcp,macaw
Classifier: Development Status :: 4 - Beta
Classifier: Intended Audience :: Developers
Classifier: License :: OSI Approved :: Apache Software License
Classifier: Programming Language :: Python :: 3
Classifier: Programming Language :: Python :: 3.9
Classifier: Programming Language :: Python :: 3.10
Classifier: Programming Language :: Python :: 3.11
Classifier: Programming Language :: Python :: 3.12
Classifier: Topic :: Security
Classifier: Topic :: Scientific/Engineering :: Artificial Intelligence
Requires-Python: >=3.9
License-File: LICENSE
License-File: NOTICE
Requires-Dist: requests>=2.28.0
Requires-Dist: cryptography>=41.0.0
Provides-Extra: openai
Requires-Dist: openai>=1.0.0; extra == "openai"
Provides-Extra: claude
Requires-Dist: anthropic>=0.18.0; extra == "claude"
Provides-Extra: langchain
Requires-Dist: langchain>=0.1.0; extra == "langchain"
Requires-Dist: langchain-openai>=0.0.5; extra == "langchain"
Requires-Dist: langchain-anthropic>=0.1.0; extra == "langchain"
Provides-Extra: mcp
Provides-Extra: all
Requires-Dist: openai>=1.0.0; extra == "all"
Requires-Dist: anthropic>=0.18.0; extra == "all"
Requires-Dist: langchain>=0.1.0; extra == "all"
Requires-Dist: langchain-openai>=0.0.5; extra == "all"
Requires-Dist: langchain-anthropic>=0.1.0; extra == "all"
Provides-Extra: dev
Requires-Dist: pytest>=7.0.0; extra == "dev"
Requires-Dist: pytest-asyncio>=0.21.0; extra == "dev"
Requires-Dist: black>=23.0.0; extra == "dev"
Requires-Dist: mypy>=1.0.0; extra == "dev"
Dynamic: license-file
